{
  "metadata": {
    "generated": "2025-12-04 00:06:04.366466",
    "coach": "Nick Saban",
    "school": "Toledo",
    "era": "2015-2025",
    "tenure_years": 11,
    "description": "Comprehensive Nick Saban coaching profile with all statistics, games, and analysis"
  },
  "summary": {
    "generated": "2025-12-04 00:06:04.366500",
    "overview": {
      "coach": "Nick Saban",
      "era": "2015-2025",
      "total_record": "90-46",
      "win_pct": 66.2,
      "total_games": 136
    },
    "coaching_records": [
      {
        "year": 2015,
        "firstName": "Nick",
        "lastName": "Saban",
        "school": "Toledo"
      },
      {
        "year": 2016,
        "firstName": "Nick",
        "lastName": "Saban",
        "school": "Toledo"
      },
      {
        "year": 2017,
        "firstName": "Nick",
        "lastName": "Saban",
        "school": "Toledo"
      },
      {
        "year": 2018,
        "firstName": "Nick",
        "lastName": "Saban",
        "school": "Toledo"
      },
      {
        "year": 2019,
        "firstName": "Nick",
        "lastName": "Saban",
        "school": "Toledo"
      },
      {
        "year": 2020,
        "firstName": "Nick",
        "lastName": "Saban",
        "school": "Toledo"
      },
      {
        "year": 2021,
        "firstName": "Nick",
        "lastName": "Saban",
        "school": "Toledo"
      },
      {
        "year": 2022,
        "firstName": "Nick",
        "lastName": "Saban",
        "school": "Toledo"
      },
      {
        "year": 2023,
        "firstName": "Nick",
        "lastName": "Saban",
        "school": "Toledo"
      },
      {
        "year": 2024,
        "firstName": "Nick",
        "lastName": "Saban",
        "school": "Toledo"
      },
      {
        "year": 2025,
        "firstName": "Nick",
        "lastName": "Saban",
        "school": "Toledo"
      }
    ]
  },
  "games": [
    {
      "id": 400603861,
      "season": 2015,
      "week": 2,
      "seasonType": "regular",
      "homeTeam": "Arkansas",
      "awayTeam": "Toledo",
      "homePoints": 12,
      "awayPoints": 16,
      "neutralSite": false,
      "excitement": 6.8413150309,
      "conferenceGame": false
    },
    {
      "id": 400763421,
      "season": 2015,
      "week": 3,
      "seasonType": "regular",
      "homeTeam": "Toledo",
      "awayTeam": "Iowa State",
      "homePoints": 30,
      "awayPoints": 23,
      "neutralSite": false,
      "excitement": 7.0527724031,
      "conferenceGame": false
    },
    {
      "id": 400787314,
      "season": 2015,
      "week": 4,
      "seasonType": "regular",
      "homeTeam": "Toledo",
      "awayTeam": "Arkansas State",
      "homePoints": 37,
      "awayPoints": 7,
      "neutralSite": false,
      "excitement": 1.36584244349999,
      "conferenceGame": false
    },
    {
      "id": 400787317,
      "season": 2015,
      "week": 5,
      "seasonType": "regular",
      "homeTeam": "Ball State",
      "awayTeam": "Toledo",
      "homePoints": 10,
      "awayPoints": 24,
      "neutralSite": false,
      "excitement": 2.5312082985,
      "conferenceGame": true
    },
    {
      "id": 400787320,
      "season": 2015,
      "week": 6,
      "seasonType": "regular",
      "homeTeam": "Toledo",
      "awayTeam": "Kent State",
      "homePoints": 38,
      "awayPoints": 7,
      "neutralSite": false,
      "excitement": 2.6593450207,
      "conferenceGame": true
    },
    {
      "id": 400787330,
      "season": 2015,
      "week": 7,
      "seasonType": "regular",
      "homeTeam": "Toledo",
      "awayTeam": "Eastern Michigan",
      "homePoints": 63,
      "awayPoints": 20,
      "neutralSite": false,
      "excitement": 1.0493583266,
      "conferenceGame": true
    },
    {
      "id": 400787338,
      "season": 2015,
      "week": 8,
      "seasonType": "regular",
      "homeTeam": "Massachusetts",
      "awayTeam": "Toledo",
      "homePoints": 35,
      "awayPoints": 51,
      "neutralSite": false,
      "excitement": 6.26823470149999,
      "conferenceGame": true
    },
    {
      "id": 400787343,
      "season": 2015,
      "week": 10,
      "seasonType": "regular",
      "homeTeam": "Toledo",
      "awayTeam": "Northern Illinois",
      "homePoints": 27,
      "awayPoints": 32,
      "neutralSite": false,
      "excitement": 7.7387324874,
      "conferenceGame": true
    },
    {
      "id": 400787350,
      "season": 2015,
      "week": 11,
      "seasonType": "regular",
      "homeTeam": "Central Michigan",
      "awayTeam": "Toledo",
      "homePoints": 23,
      "awayPoints": 28,
      "neutralSite": false,
      "excitement": 4.8491100891,
      "conferenceGame": true
    },
    {
      "id": 400787356,
      "season": 2015,
      "week": 12,
      "seasonType": "regular",
      "homeTeam": "Bowling Green",
      "awayTeam": "Toledo",
      "homePoints": 28,
      "awayPoints": 44,
      "neutralSite": false,
      "excitement": 4.8157971945,
      "conferenceGame": true
    },
    {
      "id": 400787363,
      "season": 2015,
      "week": 13,
      "seasonType": "regular",
      "homeTeam": "Toledo",
      "awayTeam": "Western Michigan",
      "homePoints": 30,
      "awayPoints": 35,
      "neutralSite": false,
      "excitement": null,
      "conferenceGame": true
    },
    {
      "id": 400869265,
      "season": 2016,
      "week": 1,
      "seasonType": "regular",
      "homeTeam": "Arkansas State",
      "awayTeam": "Toledo",
      "homePoints": 10,
      "awayPoints": 31,
      "neutralSite": false,
      "excitement": 3.1212190244,
      "conferenceGame": false
    },
    {
      "id": 400869272,
      "season": 2016,
      "week": 2,
      "seasonType": "regular",
      "homeTeam": "Toledo",
      "awayTeam": "Maine",
      "homePoints": 45,
      "awayPoints": 3,
      "neutralSite": false,
      "excitement": 0.753745363099999,
      "conferenceGame": false
    },
    {
      "id": 400869195,
      "season": 2016,
      "week": 3,
      "seasonType": "regular",
      "homeTeam": "Toledo",
      "awayTeam": "Fresno State",
      "homePoints": 52,
      "awayPoints": 17,
      "neutralSite": false,
      "excitement": 0.4995627454,
      "conferenceGame": false
    },
    {
      "id": 400868926,
      "season": 2016,
      "week": 5,
      "seasonType": "regular",
      "homeTeam": "BYU",
      "awayTeam": "Toledo",
      "homePoints": 55,
      "awayPoints": 53,
      "neutralSite": false,
      "excitement": 9.7746027262,
      "conferenceGame": false
    },
    {
      "id": 400869304,
      "season": 2016,
      "week": 6,
      "seasonType": "regular",
      "homeTeam": "Eastern Michigan",
      "awayTeam": "Toledo",
      "homePoints": 20,
      "awayPoints": 35,
      "neutralSite": false,
      "excitement": 3.1821295799,
      "conferenceGame": true
    },
    {
      "id": 400869306,
      "season": 2016,
      "week": 7,
      "seasonType": "regular",
      "homeTeam": "Toledo",
      "awayTeam": "Bowling Green",
      "homePoints": 42,
      "awayPoints": 35,
      "neutralSite": false,
      "excitement": null,
      "conferenceGame": true
    },
    {
      "id": 400869313,
      "season": 2016,
      "week": 8,
      "seasonType": "regular",
      "homeTeam": "Toledo",
      "awayTeam": "Central Michigan",
      "homePoints": 31,
      "awayPoints": 17,
      "neutralSite": false,
      "excitement": 2.95422026389999,
      "conferenceGame": true
    },
    {
      "id": 400869318,
      "season": 2016,
      "week": 9,
      "seasonType": "regular",
      "homeTeam": "Toledo",
      "awayTeam": "Ohio",
      "homePoints": 26,
      "awayPoints": 31,
      "neutralSite": false,
      "excitement": 8.0674786202,
      "conferenceGame": true
    },
    {
      "id": 400869322,
      "season": 2016,
      "week": 10,
      "seasonType": "regular",
      "homeTeam": "Akron",
      "awayTeam": "Toledo",
      "homePoints": 17,
      "awayPoints": 48,
      "neutralSite": false,
      "excitement": 3.3345780414,
      "conferenceGame": true
    },
    {
      "id": 400869328,
      "season": 2016,
      "week": 11,
      "seasonType": "regular",
      "homeTeam": "Northern Illinois",
      "awayTeam": "Toledo",
      "homePoints": 24,
      "awayPoints": 31,
      "neutralSite": true,
      "excitement": 9.0502205632,
      "conferenceGame": true
    },
    {
      "id": 400869332,
      "season": 2016,
      "week": 12,
      "seasonType": "regular",
      "homeTeam": "Toledo",
      "awayTeam": "Ball State",
      "homePoints": 37,
      "awayPoints": 19,
      "neutralSite": false,
      "excitement": 1.22553076949999,
      "conferenceGame": true
    },
    {
      "id": 400869340,
      "season": 2016,
      "week": 13,
      "seasonType": "regular",
      "homeTeam": "Western Michigan",
      "awayTeam": "Toledo",
      "homePoints": 55,
      "awayPoints": 35,
      "neutralSite": false,
      "excitement": 2.320569662,
      "conferenceGame": true
    },
    {
      "id": 400944889,
      "season": 2017,
      "week": 1,
      "seasonType": "regular",
      "homeTeam": "Toledo",
      "awayTeam": "Elon",
      "homePoints": 47,
      "awayPoints": 13,
      "neutralSite": false,
      "excitement": 0.124191380199999,
      "conferenceGame": false
    },
    {
      "id": 400944898,
      "season": 2017,
      "week": 2,
      "seasonType": "regular",
      "homeTeam": "Nevada",
      "awayTeam": "Toledo",
      "homePoints": 24,
      "awayPoints": 37,
      "neutralSite": false,
      "excitement": 3.128835146,
      "conferenceGame": false
    },
    {
      "id": 400941802,
      "season": 2017,
      "week": 3,
      "seasonType": "regular",
      "homeTeam": "Toledo",
      "awayTeam": "Tulsa",
      "homePoints": 54,
      "awayPoints": 51,
      "neutralSite": false,
      "excitement": 10.1392618717,
      "conferenceGame": false
    },
    {
      "id": 400937475,
      "season": 2017,
      "week": 4,
      "seasonType": "regular",
      "homeTeam": "Miami",
      "awayTeam": "Toledo",
      "homePoints": 52,
      "awayPoints": 30,
      "neutralSite": false,
      "excitement": 5.2666719758,
      "conferenceGame": false
    },
    {
      "id": 400944991,
      "season": 2017,
      "week": 6,
      "seasonType": "regular",
      "homeTeam": "Toledo",
      "awayTeam": "Eastern Michigan",
      "homePoints": 20,
      "awayPoints": 15,
      "neutralSite": false,
      "excitement": 5.582981676,
      "conferenceGame": true
    },
    {
      "id": 400944998,
      "season": 2017,
      "week": 7,
      "seasonType": "regular",
      "homeTeam": "Central Michigan",
      "awayTeam": "Toledo",
      "homePoints": 10,
      "awayPoints": 30,
      "neutralSite": false,
      "excitement": 2.6108742298,
      "conferenceGame": true
    },
    {
      "id": 400944999,
      "season": 2017,
      "week": 8,
      "seasonType": "regular",
      "homeTeam": "Toledo",
      "awayTeam": "Akron",
      "homePoints": 48,
      "awayPoints": 21,
      "neutralSite": false,
      "excitement": 0.8750031379,
      "conferenceGame": true
    },
    {
      "id": 400945006,
      "season": 2017,
      "week": 9,
      "seasonType": "regular",
      "homeTeam": "Ball State",
      "awayTeam": "Toledo",
      "homePoints": 17,
      "awayPoints": 58,
      "neutralSite": false,
      "excitement": 1.2747109832,
      "conferenceGame": true
    },
    {
      "id": 400945012,
      "season": 2017,
      "week": 10,
      "seasonType": "regular",
      "homeTeam": "Toledo",
      "awayTeam": "Northern Illinois",
      "homePoints": 27,
      "awayPoints": 17,
      "neutralSite": false,
      "excitement": 5.3198864019,
      "conferenceGame": true
    },
    {
      "id": 400945017,
      "season": 2017,
      "week": 11,
      "seasonType": "regular",
      "homeTeam": "Ohio",
      "awayTeam": "Toledo",
      "homePoints": 38,
      "awayPoints": 10,
      "neutralSite": false,
      "excitement": 3.91956548239999,
      "conferenceGame": true
    },
    {
      "id": 400945022,
      "season": 2017,
      "week": 12,
      "seasonType": "regular",
      "homeTeam": "Bowling Green",
      "awayTeam": "Toledo",
      "homePoints": 37,
      "awayPoints": 66,
      "neutralSite": false,
      "excitement": 2.28695675089999,
      "conferenceGame": true
    },
    {
      "id": 400945030,
      "season": 2017,
      "week": 13,
      "seasonType": "regular",
      "homeTeam": "Toledo",
      "awayTeam": "Western Michigan",
      "homePoints": 37,
      "awayPoints": 10,
      "neutralSite": false,
      "excitement": 1.9931850647,
      "conferenceGame": true
    },
    {
      "id": 400955150,
      "season": 2017,
      "week": 14,
      "seasonType": "regular",
      "homeTeam": "Toledo",
      "awayTeam": "Akron",
      "homePoints": 45,
      "awayPoints": 28,
      "neutralSite": true,
      "excitement": 0.8473251003,
      "conferenceGame": true
    },
    {
      "id": 401020676,
      "season": 2018,
      "week": 1,
      "seasonType": "regular",
      "homeTeam": "Toledo",
      "awayTeam": "VMI",
      "homePoints": 66,
      "awayPoints": 3,
      "neutralSite": false,
      "excitement": 0.0266620140000006,
      "conferenceGame": false
    },
    {
      "id": 401013114,
      "season": 2018,
      "week": 3,
      "seasonType": "regular",
      "homeTeam": "Toledo",
      "awayTeam": "Miami",
      "homePoints": 24,
      "awayPoints": 49,
      "neutralSite": false,
      "excitement": 2.996293069,
      "conferenceGame": false
    },
    {
      "id": 401020685,
      "season": 2018,
      "week": 4,
      "seasonType": "regular",
      "homeTeam": "Toledo",
      "awayTeam": "Nevada",
      "homePoints": 63,
      "awayPoints": 44,
      "neutralSite": false,
      "excitement": 4.3685790561,
      "conferenceGame": false
    },
    {
      "id": 401020689,
      "season": 2018,
      "week": 5,
      "seasonType": "regular",
      "homeTeam": "Fresno State",
      "awayTeam": "Toledo",
      "homePoints": 49,
      "awayPoints": 27,
      "neutralSite": false,
      "excitement": 2.2054180656,
      "conferenceGame": false
    },
    {
      "id": 401020751,
      "season": 2018,
      "week": 6,
      "seasonType": "regular",
      "homeTeam": "Toledo",
      "awayTeam": "Bowling Green",
      "homePoints": 52,
      "awayPoints": 36,
      "neutralSite": false,
      "excitement": 2.2676329364,
      "conferenceGame": true
    },
    {
      "id": 401020759,
      "season": 2018,
      "week": 7,
      "seasonType": "regular",
      "homeTeam": "Eastern Michigan",
      "awayTeam": "Toledo",
      "homePoints": 28,
      "awayPoints": 26,
      "neutralSite": false,
      "excitement": 3.4057041962,
      "conferenceGame": true
    },
    {
      "id": 401020763,
      "season": 2018,
      "week": 8,
      "seasonType": "regular",
      "homeTeam": "Toledo",
      "awayTeam": "Buffalo",
      "homePoints": 17,
      "awayPoints": 31,
      "neutralSite": false,
      "excitement": 6.77240794269999,
      "conferenceGame": true
    },
    {
      "id": 401020767,
      "season": 2018,
      "week": 9,
      "seasonType": "regular",
      "homeTeam": "Western Michigan",
      "awayTeam": "Toledo",
      "homePoints": 24,
      "awayPoints": 51,
      "neutralSite": false,
      "excitement": 3.29637464,
      "conferenceGame": true
    },
    {
      "id": 401020771,
      "season": 2018,
      "week": 10,
      "seasonType": "regular",
      "homeTeam": "Toledo",
      "awayTeam": "Ball State",
      "homePoints": 45,
      "awayPoints": 13,
      "neutralSite": false,
      "excitement": 0.875291844899999,
      "conferenceGame": true
    },
    {
      "id": 401020777,
      "season": 2018,
      "week": 11,
      "seasonType": "regular",
      "homeTeam": "Northern Illinois",
      "awayTeam": "Toledo",
      "homePoints": 38,
      "awayPoints": 15,
      "neutralSite": false,
      "excitement": 4.3073049603,
      "conferenceGame": true
    },
    {
      "id": 401020783,
      "season": 2018,
      "week": 12,
      "seasonType": "regular",
      "homeTeam": "Kent State",
      "awayTeam": "Toledo",
      "homePoints": 34,
      "awayPoints": 56,
      "neutralSite": false,
      "excitement": 2.5292833816,
      "conferenceGame": true
    },
    {
      "id": 401020789,
      "season": 2018,
      "week": 13,
      "seasonType": "regular",
      "homeTeam": "Toledo",
      "awayTeam": "Central Michigan",
      "homePoints": 51,
      "awayPoints": 13,
      "neutralSite": false,
      "excitement": 1.7372936855,
      "conferenceGame": true
    },
    {
      "id": 401110724,
      "season": 2019,
      "week": 1,
      "seasonType": "regular",
      "homeTeam": "Kentucky",
      "awayTeam": "Toledo",
      "homePoints": 38,
      "awayPoints": 24,
      "neutralSite": false,
      "excitement": 5.084117394,
      "conferenceGame": false
    },
    {
      "id": 401119265,
      "season": 2019,
      "week": 3,
      "seasonType": "regular",
      "homeTeam": "Toledo",
      "awayTeam": "Murray State",
      "homePoints": 45,
      "awayPoints": 0,
      "neutralSite": false,
      "excitement": 0.246662225699999,
      "conferenceGame": false
    },
    {
      "id": 401117507,
      "season": 2019,
      "week": 4,
      "seasonType": "regular",
      "homeTeam": "Colorado State",
      "awayTeam": "Toledo",
      "homePoints": 35,
      "awayPoints": 41,
      "neutralSite": false,
      "excitement": 6.9052906935,
      "conferenceGame": false
    },
    {
      "id": 401117213,
      "season": 2019,
      "week": 5,
      "seasonType": "regular",
      "homeTeam": "Toledo",
      "awayTeam": "BYU",
      "homePoints": 28,
      "awayPoints": 21,
      "neutralSite": false,
      "excitement": 8.04097262079999,
      "conferenceGame": false
    },
    {
      "id": 401119275,
      "season": 2019,
      "week": 6,
      "seasonType": "regular",
      "homeTeam": "Toledo",
      "awayTeam": "Western Michigan",
      "homePoints": 31,
      "awayPoints": 24,
      "neutralSite": false,
      "excitement": 4.9586379303,
      "conferenceGame": true
    },
    {
      "id": 401119280,
      "season": 2019,
      "week": 7,
      "seasonType": "regular",
      "homeTeam": "Bowling Green",
      "awayTeam": "Toledo",
      "homePoints": 20,
      "awayPoints": 7,
      "neutralSite": false,
      "excitement": 5.7175731394,
      "conferenceGame": true
    },
    {
      "id": 401119285,
      "season": 2019,
      "week": 8,
      "seasonType": "regular",
      "homeTeam": "Ball State",
      "awayTeam": "Toledo",
      "homePoints": 52,
      "awayPoints": 14,
      "neutralSite": false,
      "excitement": 1.44664991829999,
      "conferenceGame": true
    },
    {
      "id": 401119290,
      "season": 2019,
      "week": 9,
      "seasonType": "regular",
      "homeTeam": "Toledo",
      "awayTeam": "Eastern Michigan",
      "homePoints": 37,
      "awayPoints": 34,
      "neutralSite": false,
      "excitement": 6.1498066998,
      "conferenceGame": true
    },
    {
      "id": 401119297,
      "season": 2019,
      "week": 11,
      "seasonType": "regular",
      "homeTeam": "Toledo",
      "awayTeam": "Kent State",
      "homePoints": 35,
      "awayPoints": 33,
      "neutralSite": false,
      "excitement": 5.0533344444,
      "conferenceGame": true
    },
    {
      "id": 401119302,
      "season": 2019,
      "week": 12,
      "seasonType": "regular",
      "homeTeam": "Toledo",
      "awayTeam": "Northern Illinois",
      "homePoints": 28,
      "awayPoints": 31,
      "neutralSite": false,
      "excitement": 6.84362173409999,
      "conferenceGame": true
    },
    {
      "id": 401119308,
      "season": 2019,
      "week": 13,
      "seasonType": "regular",
      "homeTeam": "Buffalo",
      "awayTeam": "Toledo",
      "homePoints": 49,
      "awayPoints": 30,
      "neutralSite": false,
      "excitement": 2.46430895209999,
      "conferenceGame": true
    },
    {
      "id": 401119315,
      "season": 2019,
      "week": 14,
      "seasonType": "regular",
      "homeTeam": "Central Michigan",
      "awayTeam": "Toledo",
      "homePoints": 49,
      "awayPoints": 7,
      "neutralSite": false,
      "excitement": 0.893877250499999,
      "conferenceGame": true
    },
    {
      "id": 401249858,
      "season": 2020,
      "week": 10,
      "seasonType": "regular",
      "homeTeam": "Toledo",
      "awayTeam": "Bowling Green",
      "homePoints": 38,
      "awayPoints": 3,
      "neutralSite": false,
      "excitement": 1.3977801538,
      "conferenceGame": true
    },
    {
      "id": 401249866,
      "season": 2020,
      "week": 11,
      "seasonType": "regular",
      "homeTeam": "Western Michigan",
      "awayTeam": "Toledo",
      "homePoints": 41,
      "awayPoints": 38,
      "neutralSite": false,
      "excitement": 7.1435125387,
      "conferenceGame": true
    },
    {
      "id": 401249871,
      "season": 2020,
      "week": 12,
      "seasonType": "regular",
      "homeTeam": "Eastern Michigan",
      "awayTeam": "Toledo",
      "homePoints": 28,
      "awayPoints": 45,
      "neutralSite": false,
      "excitement": 2.3579136742,
      "conferenceGame": true
    },
    {
      "id": 401249873,
      "season": 2020,
      "week": 13,
      "seasonType": "regular",
      "homeTeam": "Toledo",
      "awayTeam": "Ball State",
      "homePoints": 24,
      "awayPoints": 27,
      "neutralSite": false,
      "excitement": 4.5623336447,
      "conferenceGame": true
    },
    {
      "id": 401249880,
      "season": 2020,
      "week": 14,
      "seasonType": "regular",
      "homeTeam": "Northern Illinois",
      "awayTeam": "Toledo",
      "homePoints": 24,
      "awayPoints": 41,
      "neutralSite": false,
      "excitement": 5.8685130087,
      "conferenceGame": true
    },
    {
      "id": 401249883,
      "season": 2020,
      "week": 15,
      "seasonType": "regular",
      "homeTeam": "Toledo",
      "awayTeam": "Central Michigan",
      "homePoints": 24,
      "awayPoints": 23,
      "neutralSite": false,
      "excitement": 8.1808928691,
      "conferenceGame": true
    },
    {
      "id": 401309543,
      "season": 2021,
      "week": 1,
      "seasonType": "regular",
      "homeTeam": "Toledo",
      "awayTeam": "Norfolk State",
      "homePoints": 49,
      "awayPoints": 10,
      "neutralSite": false,
      "excitement": 1.0562631389,
      "conferenceGame": false
    },
    {
      "id": 401282705,
      "season": 2021,
      "week": 2,
      "seasonType": "regular",
      "homeTeam": "Notre Dame",
      "awayTeam": "Toledo",
      "homePoints": 32,
      "awayPoints": 29,
      "neutralSite": false,
      "excitement": 8.626931184,
      "conferenceGame": false
    },
    {
      "id": 401309553,
      "season": 2021,
      "week": 3,
      "seasonType": "regular",
      "homeTeam": "Toledo",
      "awayTeam": "Colorado State",
      "homePoints": 6,
      "awayPoints": 22,
      "neutralSite": false,
      "excitement": 6.646956065,
      "conferenceGame": false
    },
    {
      "id": 401309555,
      "season": 2021,
      "week": 4,
      "seasonType": "regular",
      "homeTeam": "Ball State",
      "awayTeam": "Toledo",
      "homePoints": 12,
      "awayPoints": 22,
      "neutralSite": false,
      "excitement": 5.0530445799,
      "conferenceGame": true
    },
    {
      "id": 401286302,
      "season": 2021,
      "week": 5,
      "seasonType": "regular",
      "homeTeam": "Massachusetts",
      "awayTeam": "Toledo",
      "homePoints": 7,
      "awayPoints": 45,
      "neutralSite": false,
      "excitement": 0.7495902708,
      "conferenceGame": false
    },
    {
      "id": 401309564,
      "season": 2021,
      "week": 6,
      "seasonType": "regular",
      "homeTeam": "Toledo",
      "awayTeam": "Northern Illinois",
      "homePoints": 20,
      "awayPoints": 22,
      "neutralSite": false,
      "excitement": 9.1098998336,
      "conferenceGame": true
    },
    {
      "id": 401309569,
      "season": 2021,
      "week": 7,
      "seasonType": "regular",
      "homeTeam": "Central Michigan",
      "awayTeam": "Toledo",
      "homePoints": 26,
      "awayPoints": 23,
      "neutralSite": false,
      "excitement": 6.8338062758,
      "conferenceGame": true
    },
    {
      "id": 401309573,
      "season": 2021,
      "week": 8,
      "seasonType": "regular",
      "homeTeam": "Toledo",
      "awayTeam": "Western Michigan",
      "homePoints": 34,
      "awayPoints": 15,
      "neutralSite": false,
      "excitement": 6.9043377046,
      "conferenceGame": true
    },
    {
      "id": 401309580,
      "season": 2021,
      "week": 10,
      "seasonType": "regular",
      "homeTeam": "Toledo",
      "awayTeam": "Eastern Michigan",
      "homePoints": 49,
      "awayPoints": 52,
      "neutralSite": false,
      "excitement": 6.6910554518,
      "conferenceGame": true
    },
    {
      "id": 401309585,
      "season": 2021,
      "week": 11,
      "seasonType": "regular",
      "homeTeam": "Bowling Green",
      "awayTeam": "Toledo",
      "homePoints": 17,
      "awayPoints": 49,
      "neutralSite": false,
      "excitement": 2.0257558905,
      "conferenceGame": true
    },
    {
      "id": 401309589,
      "season": 2021,
      "week": 12,
      "seasonType": "regular",
      "homeTeam": "Ohio",
      "awayTeam": "Toledo",
      "homePoints": 23,
      "awayPoints": 35,
      "neutralSite": false,
      "excitement": 2.6260139609,
      "conferenceGame": true
    },
    {
      "id": 401309597,
      "season": 2021,
      "week": 13,
      "seasonType": "regular",
      "homeTeam": "Toledo",
      "awayTeam": "Akron",
      "homePoints": 49,
      "awayPoints": 14,
      "neutralSite": false,
      "excitement": 1.6023583066,
      "conferenceGame": true
    },
    {
      "id": 401441990,
      "season": 2022,
      "week": 1,
      "seasonType": "regular",
      "homeTeam": "Toledo",
      "awayTeam": "Long Island University",
      "homePoints": 37,
      "awayPoints": 0,
      "neutralSite": false,
      "excitement": 1.1696927417,
      "conferenceGame": false
    },
    {
      "id": 401414779,
      "season": 2022,
      "week": 2,
      "seasonType": "regular",
      "homeTeam": "Toledo",
      "awayTeam": "Massachusetts",
      "homePoints": 55,
      "awayPoints": 10,
      "neutralSite": false,
      "excitement": 2.7800511803,
      "conferenceGame": false
    },
    {
      "id": 401405088,
      "season": 2022,
      "week": 3,
      "seasonType": "regular",
      "homeTeam": "Ohio State",
      "awayTeam": "Toledo",
      "homePoints": 77,
      "awayPoints": 21,
      "neutralSite": false,
      "excitement": 1.188010074,
      "conferenceGame": false
    },
    {
      "id": 401415224,
      "season": 2022,
      "week": 4,
      "seasonType": "regular",
      "homeTeam": "San Diego State",
      "awayTeam": "Toledo",
      "homePoints": 17,
      "awayPoints": 14,
      "neutralSite": false,
      "excitement": 7.2881666871,
      "conferenceGame": false
    },
    {
      "id": 401416607,
      "season": 2022,
      "week": 5,
      "seasonType": "regular",
      "homeTeam": "Toledo",
      "awayTeam": "Central Michigan",
      "homePoints": 38,
      "awayPoints": 17,
      "neutralSite": false,
      "excitement": 3.2021495199,
      "conferenceGame": true
    },
    {
      "id": 401416615,
      "season": 2022,
      "week": 6,
      "seasonType": "regular",
      "homeTeam": "Northern Illinois",
      "awayTeam": "Toledo",
      "homePoints": 32,
      "awayPoints": 52,
      "neutralSite": false,
      "excitement": 1.2907177514,
      "conferenceGame": true
    },
    {
      "id": 401416621,
      "season": 2022,
      "week": 7,
      "seasonType": "regular",
      "homeTeam": "Toledo",
      "awayTeam": "Kent State",
      "homePoints": 52,
      "awayPoints": 31,
      "neutralSite": false,
      "excitement": 5.7751939848,
      "conferenceGame": true
    },
    {
      "id": 401416626,
      "season": 2022,
      "week": 8,
      "seasonType": "regular",
      "homeTeam": "Buffalo",
      "awayTeam": "Toledo",
      "homePoints": 34,
      "awayPoints": 27,
      "neutralSite": false,
      "excitement": 5.9953103213,
      "conferenceGame": true
    },
    {
      "id": 401416630,
      "season": 2022,
      "week": 9,
      "seasonType": "regular",
      "homeTeam": "Eastern Michigan",
      "awayTeam": "Toledo",
      "homePoints": 24,
      "awayPoints": 27,
      "neutralSite": false,
      "excitement": 6.407781482,
      "conferenceGame": true
    },
    {
      "id": 401416636,
      "season": 2022,
      "week": 11,
      "seasonType": "regular",
      "homeTeam": "Toledo",
      "awayTeam": "Ball State",
      "homePoints": 28,
      "awayPoints": 21,
      "neutralSite": false,
      "excitement": 10.096023799,
      "conferenceGame": true
    },
    {
      "id": 401416642,
      "season": 2022,
      "week": 12,
      "seasonType": "regular",
      "homeTeam": "Toledo",
      "awayTeam": "Bowling Green",
      "homePoints": 35,
      "awayPoints": 42,
      "neutralSite": false,
      "excitement": 7.6387238121,
      "conferenceGame": true
    },
    {
      "id": 401416651,
      "season": 2022,
      "week": 13,
      "seasonType": "regular",
      "homeTeam": "Western Michigan",
      "awayTeam": "Toledo",
      "homePoints": 20,
      "awayPoints": 14,
      "neutralSite": false,
      "excitement": 8.7297787595,
      "conferenceGame": true
    },
    {
      "id": 401437033,
      "season": 2022,
      "week": 14,
      "seasonType": "regular",
      "homeTeam": "Ohio",
      "awayTeam": "Toledo",
      "homePoints": 7,
      "awayPoints": 17,
      "neutralSite": true,
      "excitement": 5.5028031694,
      "conferenceGame": true
    },
    {
      "id": 401520155,
      "season": 2023,
      "week": 1,
      "seasonType": "regular",
      "homeTeam": "Illinois",
      "awayTeam": "Toledo",
      "homePoints": 30,
      "awayPoints": 28,
      "neutralSite": false,
      "excitement": 8.6001583941,
      "conferenceGame": false
    },
    {
      "id": 401532398,
      "season": 2023,
      "week": 2,
      "seasonType": "regular",
      "homeTeam": "Toledo",
      "awayTeam": "Texas Southern",
      "homePoints": 71,
      "awayPoints": 3,
      "neutralSite": false,
      "excitement": 2.3103907538,
      "conferenceGame": false
    },
    {
      "id": 401532403,
      "season": 2023,
      "week": 3,
      "seasonType": "regular",
      "homeTeam": "Toledo",
      "awayTeam": "San Jos\u00e9 State",
      "homePoints": 21,
      "awayPoints": 17,
      "neutralSite": false,
      "excitement": 8.0975645478,
      "conferenceGame": false
    },
    {
      "id": 401532406,
      "season": 2023,
      "week": 4,
      "seasonType": "regular",
      "homeTeam": "Toledo",
      "awayTeam": "Western Michigan",
      "homePoints": 49,
      "awayPoints": 31,
      "neutralSite": false,
      "excitement": 7.3499796496,
      "conferenceGame": true
    },
    {
      "id": 401532411,
      "season": 2023,
      "week": 5,
      "seasonType": "regular",
      "homeTeam": "Toledo",
      "awayTeam": "Northern Illinois",
      "homePoints": 35,
      "awayPoints": 33,
      "neutralSite": false,
      "excitement": 5.8558983131,
      "conferenceGame": true
    },
    {
      "id": 401526837,
      "season": 2023,
      "week": 6,
      "seasonType": "regular",
      "homeTeam": "Massachusetts",
      "awayTeam": "Toledo",
      "homePoints": 24,
      "awayPoints": 41,
      "neutralSite": false,
      "excitement": 5.3524379261,
      "conferenceGame": false
    },
    {
      "id": 401532419,
      "season": 2023,
      "week": 7,
      "seasonType": "regular",
      "homeTeam": "Ball State",
      "awayTeam": "Toledo",
      "homePoints": 6,
      "awayPoints": 13,
      "neutralSite": false,
      "excitement": 7.4563920795,
      "conferenceGame": true
    },
    {
      "id": 401532427,
      "season": 2023,
      "week": 8,
      "seasonType": "regular",
      "homeTeam": "Miami (OH)",
      "awayTeam": "Toledo",
      "homePoints": 17,
      "awayPoints": 21,
      "neutralSite": false,
      "excitement": 5.6163526623,
      "conferenceGame": true
    },
    {
      "id": 401532434,
      "season": 2023,
      "week": 10,
      "seasonType": "regular",
      "homeTeam": "Toledo",
      "awayTeam": "Buffalo",
      "homePoints": 31,
      "awayPoints": 13,
      "neutralSite": false,
      "excitement": 3.7952915052,
      "conferenceGame": true
    },
    {
      "id": 401532440,
      "season": 2023,
      "week": 11,
      "seasonType": "regular",
      "homeTeam": "Toledo",
      "awayTeam": "Eastern Michigan",
      "homePoints": 49,
      "awayPoints": 23,
      "neutralSite": false,
      "excitement": 2.2761599218,
      "conferenceGame": true
    },
    {
      "id": 401532443,
      "season": 2023,
      "week": 12,
      "seasonType": "regular",
      "homeTeam": "Bowling Green",
      "awayTeam": "Toledo",
      "homePoints": 31,
      "awayPoints": 32,
      "neutralSite": false,
      "excitement": 6.2071802169,
      "conferenceGame": true
    },
    {
      "id": 401532451,
      "season": 2023,
      "week": 13,
      "seasonType": "regular",
      "homeTeam": "Central Michigan",
      "awayTeam": "Toledo",
      "homePoints": 17,
      "awayPoints": 32,
      "neutralSite": false,
      "excitement": 3.8573119318,
      "conferenceGame": true
    },
    {
      "id": 401539481,
      "season": 2023,
      "week": 14,
      "seasonType": "regular",
      "homeTeam": "Toledo",
      "awayTeam": "Miami (OH)",
      "homePoints": 14,
      "awayPoints": 23,
      "neutralSite": true,
      "excitement": 7.0730201968,
      "conferenceGame": true
    },
    {
      "id": 401644728,
      "season": 2024,
      "week": 1,
      "seasonType": "regular",
      "homeTeam": "Toledo",
      "awayTeam": "Duquesne",
      "homePoints": 49,
      "awayPoints": 10,
      "neutralSite": false,
      "excitement": 3.6042805247,
      "conferenceGame": false
    },
    {
      "id": 401629040,
      "season": 2024,
      "week": 2,
      "seasonType": "regular",
      "homeTeam": "Toledo",
      "awayTeam": "Massachusetts",
      "homePoints": 38,
      "awayPoints": 23,
      "neutralSite": false,
      "excitement": 6.6782431738,
      "conferenceGame": false
    },
    {
      "id": 401628356,
      "season": 2024,
      "week": 3,
      "seasonType": "regular",
      "homeTeam": "Mississippi State",
      "awayTeam": "Toledo",
      "homePoints": 17,
      "awayPoints": 41,
      "neutralSite": false,
      "excitement": 2.3939678093,
      "conferenceGame": false
    },
    {
      "id": 401641037,
      "season": 2024,
      "week": 4,
      "seasonType": "regular",
      "homeTeam": "Western Kentucky",
      "awayTeam": "Toledo",
      "homePoints": 26,
      "awayPoints": 21,
      "neutralSite": false,
      "excitement": 7.5693083783,
      "conferenceGame": false
    },
    {
      "id": 401644684,
      "season": 2024,
      "week": 6,
      "seasonType": "regular",
      "homeTeam": "Toledo",
      "awayTeam": "Miami (OH)",
      "homePoints": 30,
      "awayPoints": 20,
      "neutralSite": false,
      "excitement": 4.3592185682,
      "conferenceGame": true
    },
    {
      "id": 401644745,
      "season": 2024,
      "week": 7,
      "seasonType": "regular",
      "homeTeam": "Buffalo",
      "awayTeam": "Toledo",
      "homePoints": 30,
      "awayPoints": 15,
      "neutralSite": false,
      "excitement": 4.9612405286,
      "conferenceGame": true
    },
    {
      "id": 401644751,
      "season": 2024,
      "week": 8,
      "seasonType": "regular",
      "homeTeam": "Northern Illinois",
      "awayTeam": "Toledo",
      "homePoints": 6,
      "awayPoints": 13,
      "neutralSite": false,
      "excitement": 7.3746354167,
      "conferenceGame": true
    },
    {
      "id": 401644754,
      "season": 2024,
      "week": 9,
      "seasonType": "regular",
      "homeTeam": "Toledo",
      "awayTeam": "Bowling Green",
      "homePoints": 26,
      "awayPoints": 41,
      "neutralSite": false,
      "excitement": 5.4645428296,
      "conferenceGame": true
    },
    {
      "id": 401644758,
      "season": 2024,
      "week": 10,
      "seasonType": "regular",
      "homeTeam": "Eastern Michigan",
      "awayTeam": "Toledo",
      "homePoints": 28,
      "awayPoints": 29,
      "neutralSite": false,
      "excitement": 6.6184400987,
      "conferenceGame": true
    },
    {
      "id": 401644765,
      "season": 2024,
      "week": 12,
      "seasonType": "regular",
      "homeTeam": "Toledo",
      "awayTeam": "Central Michigan",
      "homePoints": 37,
      "awayPoints": 10,
      "neutralSite": false,
      "excitement": 3.9677424339,
      "conferenceGame": true
    },
    {
      "id": 401644773,
      "season": 2024,
      "week": 13,
      "seasonType": "regular",
      "homeTeam": "Toledo",
      "awayTeam": "Ohio",
      "homePoints": 7,
      "awayPoints": 24,
      "neutralSite": false,
      "excitement": 5.8681395512,
      "conferenceGame": true
    },
    {
      "id": 401644775,
      "season": 2024,
      "week": 14,
      "seasonType": "regular",
      "homeTeam": "Akron",
      "awayTeam": "Toledo",
      "homePoints": 21,
      "awayPoints": 14,
      "neutralSite": false,
      "excitement": 7.1114876651,
      "conferenceGame": true
    },
    {
      "id": 401752670,
      "season": 2025,
      "week": 1,
      "seasonType": "regular",
      "homeTeam": "Kentucky",
      "awayTeam": "Toledo",
      "homePoints": 24,
      "awayPoints": 16,
      "neutralSite": false,
      "excitement": 4.645077771761659,
      "conferenceGame": false
    },
    {
      "id": 401757232,
      "season": 2025,
      "week": 2,
      "seasonType": "regular",
      "homeTeam": "Toledo",
      "awayTeam": "Western Kentucky",
      "homePoints": 45,
      "awayPoints": 21,
      "neutralSite": false,
      "excitement": 3.1943613678729137,
      "conferenceGame": false
    },
    {
      "id": 401762819,
      "season": 2025,
      "week": 3,
      "seasonType": "regular",
      "homeTeam": "Toledo",
      "awayTeam": "Morgan State",
      "homePoints": 60,
      "awayPoints": 0,
      "neutralSite": false,
      "excitement": 3.094625763358364,
      "conferenceGame": false
    },
    {
      "id": 401762820,
      "season": 2025,
      "week": 4,
      "seasonType": "regular",
      "homeTeam": "Western Michigan",
      "awayTeam": "Toledo",
      "homePoints": 14,
      "awayPoints": 13,
      "neutralSite": false,
      "excitement": 5.977110270781994,
      "conferenceGame": true
    },
    {
      "id": 401762824,
      "season": 2025,
      "week": 5,
      "seasonType": "regular",
      "homeTeam": "Toledo",
      "awayTeam": "Akron",
      "homePoints": 45,
      "awayPoints": 3,
      "neutralSite": false,
      "excitement": 2.5281850060338633,
      "conferenceGame": true
    },
    {
      "id": 401762835,
      "season": 2025,
      "week": 7,
      "seasonType": "regular",
      "homeTeam": "Bowling Green",
      "awayTeam": "Toledo",
      "homePoints": 28,
      "awayPoints": 23,
      "neutralSite": false,
      "excitement": 5.4770171226142415,
      "conferenceGame": true
    },
    {
      "id": 401762842,
      "season": 2025,
      "week": 8,
      "seasonType": "regular",
      "homeTeam": "Toledo",
      "awayTeam": "Kent State",
      "homePoints": 45,
      "awayPoints": 10,
      "neutralSite": false,
      "excitement": 4.250967090349852,
      "conferenceGame": true
    },
    {
      "id": 401752952,
      "season": 2025,
      "week": 9,
      "seasonType": "regular",
      "homeTeam": "Washington State",
      "awayTeam": "Toledo",
      "homePoints": 28,
      "awayPoints": 7,
      "neutralSite": false,
      "excitement": 3.8357891127616592,
      "conferenceGame": false
    },
    {
      "id": 401762854,
      "season": 2025,
      "week": 11,
      "seasonType": "regular",
      "homeTeam": "Toledo",
      "awayTeam": "Northern Illinois",
      "homePoints": 42,
      "awayPoints": 3,
      "neutralSite": false,
      "excitement": 3.577276611121748,
      "conferenceGame": true
    },
    {
      "id": 401762860,
      "season": 2025,
      "week": 12,
      "seasonType": "regular",
      "homeTeam": "Miami (OH)",
      "awayTeam": "Toledo",
      "homePoints": 3,
      "awayPoints": 24,
      "neutralSite": false,
      "excitement": 4.9239712173484955,
      "conferenceGame": true
    },
    {
      "id": 401762867,
      "season": 2025,
      "week": 13,
      "seasonType": "regular",
      "homeTeam": "Toledo",
      "awayTeam": "Ball State",
      "homePoints": 38,
      "awayPoints": 9,
      "neutralSite": false,
      "excitement": 3.9451780489615396,
      "conferenceGame": true
    },
    {
      "id": 401762872,
      "season": 2025,
      "week": 14,
      "seasonType": "regular",
      "homeTeam": "Central Michigan",
      "awayTeam": "Toledo",
      "homePoints": 3,
      "awayPoints": 21,
      "neutralSite": false,
      "excitement": 4.719029622814196,
      "conferenceGame": true
    },
    {
      "id": 400852709,
      "season": 2015,
      "week": 1,
      "seasonType": "postseason",
      "homeTeam": "Toledo",
      "awayTeam": "Temple",
      "homePoints": 32,
      "awayPoints": 17,
      "neutralSite": true,
      "excitement": 5.77477788789999,
      "conferenceGame": false
    },
    {
      "id": 400876040,
      "season": 2016,
      "week": 1,
      "seasonType": "postseason",
      "homeTeam": "Toledo",
      "awayTeam": "App State",
      "homePoints": 28,
      "awayPoints": 31,
      "neutralSite": true,
      "excitement": 7.60698717789999,
      "conferenceGame": false
    },
    {
      "id": 400953392,
      "season": 2017,
      "week": 1,
      "seasonType": "postseason",
      "homeTeam": "Toledo",
      "awayTeam": "App State",
      "homePoints": 0,
      "awayPoints": 34,
      "neutralSite": true,
      "excitement": 2.6335376451,
      "conferenceGame": false
    },
    {
      "id": 401032061,
      "season": 2018,
      "week": 1,
      "seasonType": "postseason",
      "homeTeam": "Toledo",
      "awayTeam": "Florida International",
      "homePoints": 32,
      "awayPoints": 35,
      "neutralSite": true,
      "excitement": 6.4065445818,
      "conferenceGame": false
    },
    {
      "id": 401331164,
      "season": 2021,
      "week": 1,
      "seasonType": "postseason",
      "homeTeam": "Toledo",
      "awayTeam": "Middle Tennessee",
      "homePoints": 24,
      "awayPoints": 31,
      "neutralSite": true,
      "excitement": 7.8572093107,
      "conferenceGame": false
    },
    {
      "id": 401442006,
      "season": 2022,
      "week": 1,
      "seasonType": "postseason",
      "homeTeam": "Toledo",
      "awayTeam": "Liberty",
      "homePoints": 21,
      "awayPoints": 19,
      "neutralSite": true,
      "excitement": 6.728284125,
      "conferenceGame": false
    },
    {
      "id": 401554566,
      "season": 2023,
      "week": 1,
      "seasonType": "postseason",
      "homeTeam": "Wyoming",
      "awayTeam": "Toledo",
      "homePoints": 16,
      "awayPoints": 15,
      "neutralSite": true,
      "excitement": 6.8750977441,
      "conferenceGame": false
    },
    {
      "id": 401677180,
      "season": 2024,
      "week": 1,
      "seasonType": "postseason",
      "homeTeam": "Toledo",
      "awayTeam": "Pittsburgh",
      "homePoints": 48,
      "awayPoints": 46,
      "neutralSite": true,
      "excitement": 11.7159615311,
      "conferenceGame": false
    }
  ],
  "rankings": [
    {
      "rank": 24,
      "points": 87,
      "poll": {
        "season": 2015,
        "week": 6
      },
      "team": {
        "school": "Toledo"
      }
    },
    {
      "rank": 22,
      "points": 237,
      "poll": {
        "season": 2015,
        "week": 7
      },
      "team": {
        "school": "Toledo"
      }
    },
    {
      "rank": 19,
      "points": 345,
      "poll": {
        "season": 2015,
        "week": 8
      },
      "team": {
        "school": "Toledo"
      }
    },
    {
      "rank": 20,
      "points": 365,
      "poll": {
        "season": 2015,
        "week": 9
      },
      "team": {
        "school": "Toledo"
      }
    },
    {
      "rank": 20,
      "points": 366,
      "poll": {
        "season": 2015,
        "week": 10
      },
      "team": {
        "school": "Toledo"
      }
    },
    {
      "rank": 24,
      "points": 123,
      "poll": {
        "season": 2015,
        "week": 13
      },
      "team": {
        "school": "Toledo"
      }
    },
    {
      "rank": 23,
      "points": 118,
      "poll": {
        "season": 2023,
        "week": 13
      },
      "team": {
        "school": "Toledo"
      }
    },
    {
      "rank": 23,
      "points": 176,
      "poll": {
        "season": 2023,
        "week": 14
      },
      "team": {
        "school": "Toledo"
      }
    }
  ],
  "draft_picks": [
    {
      "year": 2017,
      "round": 3,
      "overall": 86,
      "name": "Kareem Hunt",
      "position": {
        "abbreviation": "RB"
      },
      "draftTeam": {
        "displayName": "Kansas City Chiefs"
      },
      "height": 71,
      "weight": 216
    },
    {
      "year": 2017,
      "round": 4,
      "overall": 127,
      "name": "Michael Roberts",
      "position": {
        "abbreviation": "TE"
      },
      "draftTeam": {
        "displayName": "Detroit Lions"
      },
      "height": 76,
      "weight": 270
    },
    {
      "year": 2017,
      "round": 7,
      "overall": 244,
      "name": "Treyvon Hester",
      "position": {
        "abbreviation": "DT"
      },
      "draftTeam": {
        "displayName": "Las Vegas Raiders"
      },
      "height": 74,
      "weight": 300
    },
    {
      "year": 2018,
      "round": 7,
      "overall": 249,
      "name": "Logan Woodside",
      "position": {
        "abbreviation": "QB"
      },
      "draftTeam": {
        "displayName": "Cincinnati Bengals"
      },
      "height": 73,
      "weight": 213
    },
    {
      "year": 2019,
      "round": 3,
      "overall": 66,
      "name": "Diontae Johnson",
      "position": {
        "abbreviation": "WR"
      },
      "draftTeam": {
        "displayName": "Pittsburgh Steelers"
      },
      "height": 71,
      "weight": 183
    },
    {
      "year": 2019,
      "round": 6,
      "overall": 185,
      "name": "Ka'dar Hollman",
      "position": {
        "abbreviation": "CB"
      },
      "draftTeam": {
        "displayName": "Green Bay Packers"
      },
      "height": 72,
      "weight": 196
    },
    {
      "year": 2022,
      "round": 5,
      "overall": 166,
      "name": "Tycen Anderson",
      "position": {
        "abbreviation": "S"
      },
      "draftTeam": {
        "displayName": "Cincinnati Bengals"
      },
      "height": 74,
      "weight": 209
    },
    {
      "year": 2022,
      "round": 5,
      "overall": 172,
      "name": "Samuel Womack",
      "position": {
        "abbreviation": "CB"
      },
      "draftTeam": {
        "displayName": "San Francisco 49ers"
      },
      "height": 70,
      "weight": 187
    },
    {
      "year": 2023,
      "round": 7,
      "overall": 259,
      "name": "Desjuan Johnson",
      "position": {
        "abbreviation": "DE"
      },
      "draftTeam": {
        "displayName": "Los Angeles Rams"
      },
      "height": null,
      "weight": null
    },
    {
      "year": 2024,
      "round": 1,
      "overall": 22,
      "name": "Quinyon Mitchell",
      "position": {
        "abbreviation": "CB"
      },
      "draftTeam": {
        "displayName": "Philadelphia Eagles"
      },
      "height": 72,
      "weight": 195
    },
    {
      "year": 2025,
      "round": 3,
      "overall": 65,
      "name": "Darius Alexander",
      "position": {
        "abbreviation": "DT"
      },
      "draftTeam": {
        "displayName": "New York Giants"
      },
      "height": 76,
      "weight": 305
    }
  ],
  "talent_ratings": [
    {
      "year": 2015,
      "talent": 429.03,
      "team": {
        "school": "Toledo"
      }
    },
    {
      "year": 2016,
      "talent": 460.86,
      "team": {
        "school": "Toledo"
      }
    },
    {
      "year": 2017,
      "talent": 366.47,
      "team": {
        "school": "Toledo"
      }
    },
    {
      "year": 2018,
      "talent": 463.96,
      "team": {
        "school": "Toledo"
      }
    },
    {
      "year": 2019,
      "talent": 451.43,
      "team": {
        "school": "Toledo"
      }
    },
    {
      "year": 2020,
      "talent": 391.54,
      "team": {
        "school": "Toledo"
      }
    },
    {
      "year": 2021,
      "talent": 465.4,
      "team": {
        "school": "Toledo"
      }
    },
    {
      "year": 2022,
      "talent": 498.98,
      "team": {
        "school": "Toledo"
      }
    },
    {
      "year": 2023,
      "talent": 497.64,
      "team": {
        "school": "Toledo"
      }
    },
    {
      "year": 2024,
      "talent": 571.92,
      "team": {
        "school": "Toledo"
      }
    },
    {
      "year": 2025,
      "talent": 620.13,
      "team": {
        "school": "Toledo"
      }
    }
  ],
  "betting_lines_2025": [
    {
      "id": 401752670,
      "season": 2025,
      "week": 1,
      "homeTeam": "Kentucky",
      "awayTeam": "Toledo",
      "homePoints": 24,
      "awayPoints": 16,
      "lines": [
        {
          "provider": {
            "name": "DraftKings"
          },
          "spread": -10,
          "overUnder": 48.5
        },
        {
          "provider": {
            "name": "ESPN Bet"
          },
          "spread": -9.5,
          "overUnder": 48.5
        },
        {
          "provider": {
            "name": "Bovada"
          },
          "spread": -10.0,
          "overUnder": 49
        }
      ]
    },
    {
      "id": 401757232,
      "season": 2025,
      "week": 2,
      "homeTeam": "Toledo",
      "awayTeam": "Western Kentucky",
      "homePoints": 45,
      "awayPoints": 21,
      "lines": [
        {
          "provider": {
            "name": "Bovada"
          },
          "spread": -8.5,
          "overUnder": 57.5
        },
        {
          "provider": {
            "name": "ESPN Bet"
          },
          "spread": -7.5,
          "overUnder": 56.5
        }
      ]
    },
    {
      "id": 401762819,
      "season": 2025,
      "week": 3,
      "homeTeam": "Toledo",
      "awayTeam": "Morgan State",
      "homePoints": 60,
      "awayPoints": 0,
      "lines": [
        {
          "provider": {
            "name": "DraftKings"
          },
          "spread": -33.5,
          "overUnder": 54.5
        },
        {
          "provider": {
            "name": "ESPN Bet"
          },
          "spread": -33.5,
          "overUnder": 54.5
        },
        {
          "provider": {
            "name": "Bovada"
          },
          "spread": -34.0,
          "overUnder": 54.5
        }
      ]
    },
    {
      "id": 401762820,
      "season": 2025,
      "week": 4,
      "homeTeam": "Western Michigan",
      "awayTeam": "Toledo",
      "homePoints": 14,
      "awayPoints": 13,
      "lines": [
        {
          "provider": {
            "name": "DraftKings"
          },
          "spread": 13.5,
          "overUnder": 48.5
        },
        {
          "provider": {
            "name": "Bovada"
          },
          "spread": 13.0,
          "overUnder": 48.5
        },
        {
          "provider": {
            "name": "ESPN Bet"
          },
          "spread": 11.5,
          "overUnder": 48.5
        }
      ]
    },
    {
      "id": 401762824,
      "season": 2025,
      "week": 5,
      "homeTeam": "Toledo",
      "awayTeam": "Akron",
      "homePoints": 45,
      "awayPoints": 3,
      "lines": [
        {
          "provider": {
            "name": "DraftKings"
          },
          "spread": -21.5,
          "overUnder": 50.5
        },
        {
          "provider": {
            "name": "Bovada"
          },
          "spread": -21.0,
          "overUnder": 50
        },
        {
          "provider": {
            "name": "ESPN Bet"
          },
          "spread": -22.5,
          "overUnder": 49.5
        }
      ]
    },
    {
      "id": 401762835,
      "season": 2025,
      "week": 7,
      "homeTeam": "Bowling Green",
      "awayTeam": "Toledo",
      "homePoints": 28,
      "awayPoints": 23,
      "lines": [
        {
          "provider": {
            "name": "DraftKings"
          },
          "spread": 10.5,
          "overUnder": 45.5
        },
        {
          "provider": {
            "name": "Bovada"
          },
          "spread": 11.0,
          "overUnder": 46
        },
        {
          "provider": {
            "name": "ESPN Bet"
          },
          "spread": 10.5,
          "overUnder": 45.5
        }
      ]
    },
    {
      "id": 401762842,
      "season": 2025,
      "week": 8,
      "homeTeam": "Toledo",
      "awayTeam": "Kent State",
      "homePoints": 45,
      "awayPoints": 10,
      "lines": [
        {
          "provider": {
            "name": "DraftKings"
          },
          "spread": -25.5,
          "overUnder": 48.5
        },
        {
          "provider": {
            "name": "Bovada"
          },
          "spread": -25.0,
          "overUnder": 48.5
        },
        {
          "provider": {
            "name": "ESPN Bet"
          },
          "spread": -25.5,
          "overUnder": 48.5
        }
      ]
    },
    {
      "id": 401752952,
      "season": 2025,
      "week": 9,
      "homeTeam": "Washington State",
      "awayTeam": "Toledo",
      "homePoints": 28,
      "awayPoints": 7,
      "lines": [
        {
          "provider": {
            "name": "DraftKings"
          },
          "spread": 1.5,
          "overUnder": 44.5
        },
        {
          "provider": {
            "name": "ESPN Bet"
          },
          "spread": 1.5,
          "overUnder": 45.5
        },
        {
          "provider": {
            "name": "Bovada"
          },
          "spread": 2.0,
          "overUnder": 44.5
        }
      ]
    },
    {
      "id": 401762854,
      "season": 2025,
      "week": 11,
      "homeTeam": "Toledo",
      "awayTeam": "Northern Illinois",
      "homePoints": 42,
      "awayPoints": 3,
      "lines": [
        {
          "provider": {
            "name": "DraftKings"
          },
          "spread": -14.5,
          "overUnder": 42.5
        },
        {
          "provider": {
            "name": "ESPN Bet"
          },
          "spread": -15.5,
          "overUnder": 41.5
        },
        {
          "provider": {
            "name": "Bovada"
          },
          "spread": -15.5,
          "overUnder": 42
        }
      ]
    },
    {
      "id": 401762860,
      "season": 2025,
      "week": 12,
      "homeTeam": "Miami (OH)",
      "awayTeam": "Toledo",
      "homePoints": 3,
      "awayPoints": 24,
      "lines": [
        {
          "provider": {
            "name": "ESPN Bet"
          },
          "spread": 6.5,
          "overUnder": 44.5
        },
        {
          "provider": {
            "name": "DraftKings"
          },
          "spread": 5.5,
          "overUnder": 44.5
        },
        {
          "provider": {
            "name": "Bovada"
          },
          "spread": 5.5,
          "overUnder": 44
        }
      ]
    },
    {
      "id": 401762867,
      "season": 2025,
      "week": 13,
      "homeTeam": "Toledo",
      "awayTeam": "Ball State",
      "homePoints": 38,
      "awayPoints": 9,
      "lines": [
        {
          "provider": {
            "name": "DraftKings"
          },
          "spread": -29.5,
          "overUnder": 45.5
        },
        {
          "provider": {
            "name": "Bovada"
          },
          "spread": -29.5,
          "overUnder": 45.5
        },
        {
          "provider": {
            "name": "ESPN Bet"
          },
          "spread": -28.5,
          "overUnder": 45.5
        }
      ]
    },
    {
      "id": 401762872,
      "season": 2025,
      "week": 14,
      "homeTeam": "Central Michigan",
      "awayTeam": "Toledo",
      "homePoints": 3,
      "awayPoints": 21,
      "lines": [
        {
          "provider": {
            "name": "Bovada"
          },
          "spread": 11.5,
          "overUnder": 46.5
        },
        {
          "provider": {
            "name": "ESPN Bet"
          },
          "spread": 10.5,
          "overUnder": 46.5
        },
        {
          "provider": {
            "name": "DraftKings"
          },
          "spread": 11.5,
          "overUnder": 46.5
        }
      ]
    }
  ]
}